lightlab/__init__.py
lightlab/command_line.py
lightlab/equipment/__init__.py
lightlab/equipment/abstract_drivers/TekScopeAbstract.py
lightlab/equipment/abstract_drivers/__init__.py
lightlab/equipment/abstract_drivers/configurable.py
lightlab/equipment/abstract_drivers/electrical_sources.py
lightlab/equipment/abstract_drivers/multimodule_configurable.py
lightlab/equipment/abstract_drivers/power_meters.py
lightlab/equipment/lab_instruments/Advantest_Q8221_PM.py
lightlab/equipment/lab_instruments/Agilent_33220_FG.py
lightlab/equipment/lab_instruments/Agilent_83712B_clock.py
lightlab/equipment/lab_instruments/Agilent_N5183A_VG.py
lightlab/equipment/lab_instruments/Agilent_N5222A_NA.py
lightlab/equipment/lab_instruments/Anritsu_MP1763B_PPG.py
lightlab/equipment/lab_instruments/Apex_AP2440A_OSA.py
lightlab/equipment/lab_instruments/Arduino_Instrument.py
lightlab/equipment/lab_instruments/HP_8116A_FG.py
lightlab/equipment/lab_instruments/HP_8152A_PM.py
lightlab/equipment/lab_instruments/HP_8156A_VA.py
lightlab/equipment/lab_instruments/ILX_7900B_LS.py
lightlab/equipment/lab_instruments/Keithley_2400_SM.py
lightlab/equipment/lab_instruments/NI_PCI_6723.py
lightlab/equipment/lab_instruments/RandS_SMBV100A_VG.py
lightlab/equipment/lab_instruments/Tektronix_CSA8000_CAS.py
lightlab/equipment/lab_instruments/Tektronix_DPO4032_Oscope.py
lightlab/equipment/lab_instruments/Tektronix_DPO4034_Oscope.py
lightlab/equipment/lab_instruments/Tektronix_DSA8300_Oscope.py
lightlab/equipment/lab_instruments/Tektronix_RSA6120B_RFSA.py
lightlab/equipment/lab_instruments/Tektronix_TDS6154C_Oscope.py
lightlab/equipment/lab_instruments/__init__.py
lightlab/equipment/visa_bases/__init__.py
lightlab/equipment/visa_bases/visa_driver.py
lightlab/equipment/visa_bases/visa_object.py
lightlab/laboratory/__init__.py
lightlab/laboratory/devices.py
lightlab/laboratory/experiments.py
lightlab/laboratory/state.py
lightlab/laboratory/virtualization.py
lightlab-1.0.2.dist-info/DESCRIPTION.rst
lightlab-1.0.2.dist-info/LICENSE.txt
lightlab-1.0.2.dist-info/METADATA
lightlab-1.0.2.dist-info/RECORD
lightlab-1.0.2.dist-info/WHEEL
lightlab-1.0.2.dist-info/entry_points.txt
lightlab-1.0.2.dist-info/metadata.json
lightlab-1.0.2.dist-info/top_level.txt
