Metadata-Version: 2.0
Name: lightlab
Version: 1.0.2
Summary: Lightwave Lab instrument automation tools
Home-page: UNKNOWN
Author: UNKNOWN
Author-email: UNKNOWN
License: MIT License
Requires-Dist: dpath
Requires-Dist: jsonpickle
Requires-Dist: matplotlib
Requires-Dist: IPython
Requires-Dist: PyVISA
Requires-Dist: scipy
Requires-Dist: sklearn
Requires-Dist: dill
